paylink_protocol/__init__.py
paylink_protocol/core.py
paylink_protocol/model.py
paylink_protocol/resources.py
paylink_protocol/tier.py
paylink_protocol/util.py
paylink_protocol-1.2.2.dist-info/licenses/LICENSE
paylink_protocol-1.2.2.dist-info/METADATA
paylink_protocol-1.2.2.dist-info/WHEEL
paylink_protocol-1.2.2.dist-info/top_level.txt
paylink_protocol-1.2.2.dist-info/RECORD
