Metadata-Version: 2.4
Name: paylink_protocol
Version: 1.2.2
Summary: Monetize your digital goods with ease using the Ethereum Blockchain and the Paylink Protocol
Author-email: Paylink Protocol <mail@paylinkprotocol.com>
Requires-Python: >=3.7
License-File: LICENSE
Requires-Dist: web3
Requires-Dist: requests
Requires-Dist: eth-abi
Requires-Dist: pycryptodome
Requires-Dist: cachetools
Dynamic: license-file
